Metadata-Version: 2.1
Name: antigrav
Version: 1.1.1
Summary: antigrav is basically JSON but supports complex numbers
Home-page: 
Author: tema5002
Author-email: xtema5002x@gmail.com
Keywords: kreisi
Classifier: Development Status :: 5 - Production/Stable
Classifier: Intended Audience :: Education
Classifier: Operating System :: Microsoft :: Windows :: Windows 11
Classifier: Programming Language :: Python :: 3
